dynamicfield/__init__.py
dynamicfield/admin.py
dynamicfield/apps.py
dynamicfield/example.py
dynamicfield/forms.py
dynamicfield/models.py
dynamicfield/migrations/__init__.py
django_dynamic_field-0.0.1.dist-info/LICENSE
django_dynamic_field-0.0.1.dist-info/METADATA
django_dynamic_field-0.0.1.dist-info/WHEEL
django_dynamic_field-0.0.1.dist-info/top_level.txt
django_dynamic_field-0.0.1.dist-info/RECORD
